ete4/__init__.py
ete4/citation.py
ete4/config.py
ete4/utils.py
ete4/version.py
ete4/core/__init__.py
ete4/core/operations.c
ete4/core/seqgroup.py
ete4/core/text_viz.py
ete4/core/tree.c
ete4/evol/__init__.py
ete4/evol/control.py
ete4/evol/evoltree.py
ete4/evol/model.py
ete4/evol/utils.py
ete4/evol/parser/__init__.py
ete4/evol/parser/codemlparser.py
ete4/evol/parser/slrparser.py
ete4/gtdb_taxonomy/__init__.py
ete4/gtdb_taxonomy/gtdbquery.py
ete4/ncbi_taxonomy/__init__.py
ete4/ncbi_taxonomy/ncbiquery.py
ete4/orthoxml/__init__.py
ete4/orthoxml/_orthoxml.py
ete4/parser/__init__.py
ete4/parser/ete_format.py
ete4/parser/fasta.py
ete4/parser/indent.py
ete4/parser/newick.c
ete4/parser/nexus.py
ete4/parser/paml.py
ete4/parser/phylip.py
ete4/phylo/__init__.py
ete4/phylo/evolevents.py
ete4/phylo/phylotree.py
ete4/phylo/reconciliation.py
ete4/phylo/spoverlap.py
ete4/phyloxml/__init__.py
ete4/phyloxml/_phyloxml.py
ete4/phyloxml/_phyloxml_tree.py
ete4/smartview/__init__.py
ete4/smartview/coordinates.py
ete4/smartview/draw.py
ete4/smartview/explorer.py
ete4/smartview/faces.py
ete4/smartview/graphics.py
ete4/smartview/layout.py
ete4/smartview/static/gui.css
ete4/smartview/static/gui.html
ete4/smartview/static/upload.css
ete4/smartview/static/upload.html
ete4/smartview/static/external/pixi.min.mjs
ete4/smartview/static/external/readme.md
ete4/smartview/static/external/sweetalert2.min.js
ete4/smartview/static/external/tweakpane.min.js
ete4/smartview/static/images/icon.png
ete4/smartview/static/images/spritesheet.json
ete4/smartview/static/images/spritesheet.png
ete4/smartview/static/js/api.js
ete4/smartview/static/js/collapse.js
ete4/smartview/static/js/contextmenu.js
ete4/smartview/static/js/download.js
ete4/smartview/static/js/drag.js
ete4/smartview/static/js/draw.js
ete4/smartview/static/js/events.js
ete4/smartview/static/js/gui.js
ete4/smartview/static/js/label.js
ete4/smartview/static/js/menu.js
ete4/smartview/static/js/minimap.js
ete4/smartview/static/js/pixi.js
ete4-4.0.0.dist-info/licenses/LICENSE
ete4-4.0.0.dist-info/METADATA
ete4-4.0.0.dist-info/WHEEL
ete4-4.0.0.dist-info/entry_points.txt
ete4-4.0.0.dist-info/top_level.txt
ete4-4.0.0.dist-info/RECORD
