Metadata-Version: 2.4
Name: ete4
Version: 4.0.0
Summary: A Python Environment for (phylogenetic) Tree Exploration
Author-email: Jaime Huerta-Cepas <jhcepas@gmail.com>, Jordi Burguet-Castell <jordi.burguet.castell@gmail.com>
License-Expression: GPL-3.0-or-later
Project-URL: Homepage, http://etetoolkit.org
Classifier: Programming Language :: Python :: 3
Classifier: Development Status :: 6 - Mature
Classifier: Environment :: Console
Classifier: Environment :: X11 Applications :: Qt
Classifier: Intended Audience :: Developers
Classifier: Intended Audience :: Other Audience
Classifier: Intended Audience :: Science/Research
Classifier: Natural Language :: English
Classifier: Operating System :: MacOS
Classifier: Operating System :: Microsoft :: Windows
Classifier: Operating System :: POSIX :: Linux
Classifier: Topic :: Scientific/Engineering :: Bio-Informatics
Classifier: Topic :: Scientific/Engineering :: Visualization
Classifier: Topic :: Software Development :: Libraries :: Python Modules
Requires-Python: >=3.7
License-File: LICENSE
Requires-Dist: bottle
Requires-Dist: brotli
Requires-Dist: numpy
Requires-Dist: scipy
Requires-Dist: requests
Provides-Extra: treeview
Requires-Dist: pyqt6; extra == "treeview"
Provides-Extra: render-sm
Requires-Dist: selenium; extra == "render-sm"
Provides-Extra: treediff
Requires-Dist: lap; extra == "treediff"
Provides-Extra: test
Requires-Dist: pytest>=6.0; extra == "test"
Provides-Extra: doc
Requires-Dist: sphinx; extra == "doc"
Dynamic: license-file
